LICENSE
README.md
setup.cfg
setup.py
AshUtils/AshUtils.py
AshUtils/__init__.py
AshUtils.egg-info/PKG-INFO
AshUtils.egg-info/SOURCES.txt
AshUtils.egg-info/dependency_links.txt
AshUtils.egg-info/requires.txt
AshUtils.egg-info/top_level.txt