Metadata-Version: 2.1
Name: AshUtils
Version: 0.1
Summary: Boost productivity in Django projects with a comprehensive collection of reusable utilities and decorators.
Home-page: https://github.com/ashfaque/AshUtils
Download-URL: https://github.com/ashfaque/AshUtils/archive/refs/tags/v_01.tar.gz
Author: Ashfaque Alam
Author-email: ashfaquealam496@yahoo.com
License: GNU GPLv3
Keywords: ASHFAQUE,ASHFAQUE ALAM,DJANGO,UTILS,DRF,DECORATORS
Classifier: Development Status :: 5 - Production/Stable
Classifier: Intended Audience :: Developers
Classifier: Topic :: Software Development :: Build Tools
Classifier: Topic :: Software Development :: Libraries :: Python Modules
Classifier: License :: OSI Approved :: GNU General Public License (GPL)
Classifier: Operating System :: OS Independent
Classifier: Programming Language :: Python :: 3
Classifier: Programming Language :: Python :: 3 :: Only
Classifier: Programming Language :: Python :: 3.5
Classifier: Programming Language :: Python :: 3.6
Classifier: Programming Language :: Python :: 3.7
Classifier: Programming Language :: Python :: 3.8
Classifier: Programming Language :: Python :: 3.9
Classifier: Programming Language :: Python :: 3.10
Classifier: Programming Language :: Python :: 3.11
Classifier: Programming Language :: Python :: 3.12
License-File: LICENSE
Requires-Dist: django-redisAshLogger>=0.4
